[
  {
    "id": "c6e73840-cad8-4ea9-8cf0-59eacb2aa810",
    "project_id": "6350ccfc-2d23-4840-ac56-cf32ddd52803",
    "title": "Planejar escopo primário da aplicação",
    "completed": false,
    "completed_at": null,
    "created_at": "2026-03-10T15:14:54.60511+00:00",
    "updated_at": "2026-03-10T15:14:54.60511+00:00",
    "estimated_hours": null,
    "sort_order": 0,
    "scrum_status": "TODO",
    "description": null,
    "sprint_week": null
  },
  {
    "id": "f6e198d8-1d28-466a-b59c-670bd68d0756",
    "project_id": "6350ccfc-2d23-4840-ac56-cf32ddd52803",
    "title": "Definir ID Visual",
    "completed": false,
    "completed_at": null,
    "created_at": "2026-03-10T15:14:54.60511+00:00",
    "updated_at": "2026-03-10T15:14:54.60511+00:00",
    "estimated_hours": null,
    "sort_order": 1,
    "scrum_status": "TODO",
    "description": null,
    "sprint_week": null
  },
  {
    "id": "8c60ee97-350c-47df-bc5c-4d55104d4143",
    "project_id": "6350ccfc-2d23-4840-ac56-cf32ddd52803",
    "title": "Regras de negócio - Fluxograma de permissões e atividades da plataforma",
    "completed": false,
    "completed_at": null,
    "created_at": "2026-03-10T15:14:54.60511+00:00",
    "updated_at": "2026-03-10T15:14:54.60511+00:00",
    "estimated_hours": null,
    "sort_order": 2,
    "scrum_status": "TODO",
    "description": null,
    "sprint_week": null
  },
  {
    "id": "e6cde4f2-3142-4e0a-bb56-934508e85f04",
    "project_id": "6350ccfc-2d23-4840-ac56-cf32ddd52803",
    "title": "Protótipo de alta fidelidade - Figma",
    "completed": false,
    "completed_at": null,
    "created_at": "2026-03-10T15:14:54.60511+00:00",
    "updated_at": "2026-03-10T15:14:54.60511+00:00",
    "estimated_hours": null,
    "sort_order": 3,
    "scrum_status": "TODO",
    "description": null,
    "sprint_week": null
  },
  {
    "id": "1e1fcc9d-c414-4ebe-8c5d-0f748fa4d820",
    "project_id": "6350ccfc-2d23-4840-ac56-cf32ddd52803",
    "title": "Organização de pastas da IDE",
    "completed": false,
    "completed_at": null,
    "created_at": "2026-03-10T15:14:54.60511+00:00",
    "updated_at": "2026-03-10T15:14:54.60511+00:00",
    "estimated_hours": null,
    "sort_order": 4,
    "scrum_status": "TODO",
    "description": null,
    "sprint_week": null
  },
  {
    "id": "149cb6ca-f6e1-40ab-ab93-ed9221e1e9a8",
    "project_id": "6350ccfc-2d23-4840-ac56-cf32ddd52803",
    "title": "Fazer o front-end no código",
    "completed": false,
    "completed_at": null,
    "created_at": "2026-03-10T15:14:54.60511+00:00",
    "updated_at": "2026-03-10T15:14:54.60511+00:00",
    "estimated_hours": null,
    "sort_order": 5,
    "scrum_status": "TODO",
    "description": null,
    "sprint_week": null
  },
  {
    "id": "a8d32fb9-05d1-4f76-9b35-fe237cfbc9f7",
    "project_id": "6350ccfc-2d23-4840-ac56-cf32ddd52803",
    "title": "Backend ligado ao front",
    "completed": false,
    "completed_at": null,
    "created_at": "2026-03-10T15:14:54.60511+00:00",
    "updated_at": "2026-03-10T15:14:54.60511+00:00",
    "estimated_hours": null,
    "sort_order": 6,
    "scrum_status": "TODO",
    "description": null,
    "sprint_week": null
  },
  {
    "id": "fa7a0917-396d-4c7d-974b-57464735e580",
    "project_id": "6350ccfc-2d23-4840-ac56-cf32ddd52803",
    "title": "Banco de dados da plataforma",
    "completed": false,
    "completed_at": null,
    "created_at": "2026-03-10T15:14:54.60511+00:00",
    "updated_at": "2026-03-10T15:14:54.60511+00:00",
    "estimated_hours": null,
    "sort_order": 7,
    "scrum_status": "TODO",
    "description": null,
    "sprint_week": null
  },
  {
    "id": "386dbeba-55a2-4d1f-95d5-4cd9f877f530",
    "project_id": "6350ccfc-2d23-4840-ac56-cf32ddd52803",
    "title": "API da plataforma",
    "completed": false,
    "completed_at": null,
    "created_at": "2026-03-10T15:14:54.60511+00:00",
    "updated_at": "2026-03-10T15:14:54.60511+00:00",
    "estimated_hours": null,
    "sort_order": 8,
    "scrum_status": "TODO",
    "description": null,
    "sprint_week": null
  },
  {
    "id": "3e27d56f-eb88-42dc-a987-97fdd9fc83f9",
    "project_id": "6350ccfc-2d23-4840-ac56-cf32ddd52803",
    "title": "Estruturar em módulos - Módulo de cadastro, login, upload...",
    "completed": false,
    "completed_at": null,
    "created_at": "2026-03-10T15:14:54.60511+00:00",
    "updated_at": "2026-03-10T15:14:54.60511+00:00",
    "estimated_hours": null,
    "sort_order": 9,
    "scrum_status": "TODO",
    "description": null,
    "sprint_week": null
  },
  {
    "id": "8336e288-dcf2-4fd1-9d15-7b835cd5d381",
    "project_id": "6350ccfc-2d23-4840-ac56-cf32ddd52803",
    "title": "História do usuário",
    "completed": false,
    "completed_at": null,
    "created_at": "2026-03-10T15:14:54.60511+00:00",
    "updated_at": "2026-03-10T15:14:54.60511+00:00",
    "estimated_hours": null,
    "sort_order": 10,
    "scrum_status": "TODO",
    "description": null,
    "sprint_week": null
  },
  {
    "id": "13b981a1-17a9-40f1-8a09-859d355e2668",
    "project_id": "6350ccfc-2d23-4840-ac56-cf32ddd52803",
    "title": "Testes e manutenções",
    "completed": false,
    "completed_at": null,
    "created_at": "2026-03-10T15:14:54.60511+00:00",
    "updated_at": "2026-03-10T15:14:54.60511+00:00",
    "estimated_hours": null,
    "sort_order": 11,
    "scrum_status": "TODO",
    "description": null,
    "sprint_week": null
  },
  {
    "id": "10690118-867b-4ebe-8c01-344c3e5d5985",
    "project_id": "6350ccfc-2d23-4840-ac56-cf32ddd52803",
    "title": "Primeira versão de teste",
    "completed": false,
    "completed_at": null,
    "created_at": "2026-03-10T15:14:54.60511+00:00",
    "updated_at": "2026-03-10T15:14:54.60511+00:00",
    "estimated_hours": null,
    "sort_order": 12,
    "scrum_status": "TODO",
    "description": null,
    "sprint_week": null
  },
  {
    "id": "a7ae105b-d2ec-4e45-9723-1e4d5f5cfbfe",
    "project_id": "6350ccfc-2d23-4840-ac56-cf32ddd52803",
    "title": "Validação e Manutenções",
    "completed": false,
    "completed_at": null,
    "created_at": "2026-03-10T15:14:54.60511+00:00",
    "updated_at": "2026-03-10T15:14:54.60511+00:00",
    "estimated_hours": null,
    "sort_order": 13,
    "scrum_status": "TODO",
    "description": null,
    "sprint_week": null
  },
  {
    "id": "3f37b6f1-9221-4456-a7c2-8dbfe2f6b7e0",
    "project_id": "6350ccfc-2d23-4840-ac56-cf32ddd52803",
    "title": "Fase DEMO",
    "completed": false,
    "completed_at": null,
    "created_at": "2026-03-10T15:14:54.60511+00:00",
    "updated_at": "2026-03-10T15:14:54.60511+00:00",
    "estimated_hours": null,
    "sort_order": 14,
    "scrum_status": "TODO",
    "description": null,
    "sprint_week": null
  },
  {
    "id": "c5cda8d9-9939-4903-b729-f757bbffe497",
    "project_id": "6350ccfc-2d23-4840-ac56-cf32ddd52803",
    "title": "Versão final",
    "completed": false,
    "completed_at": null,
    "created_at": "2026-03-10T15:14:54.60511+00:00",
    "updated_at": "2026-03-10T15:14:54.60511+00:00",
    "estimated_hours": null,
    "sort_order": 15,
    "scrum_status": "TODO",
    "description": null,
    "sprint_week": null
  },
  {
    "id": "4dd9d5c6-7f09-458e-ba1a-fdecf6628b62",
    "project_id": "5ace6094-b0f4-4204-bffe-726eea930629",
    "title": "Reunir todos os dados - Planilhas e Métricas",
    "completed": false,
    "completed_at": null,
    "created_at": "2026-03-10T15:25:49.892731+00:00",
    "updated_at": "2026-03-10T15:25:49.892731+00:00",
    "estimated_hours": null,
    "sort_order": 0,
    "scrum_status": "TODO",
    "description": null,
    "sprint_week": null
  },
  {
    "id": "ef08ba97-7022-41f4-b906-d562da1eea38",
    "project_id": "95668618-c7aa-4770-a484-a1df5d8d02e7",
    "title": "Primeira versão de teste",
    "completed": false,
    "completed_at": null,
    "created_at": "2026-03-10T14:44:46.681464+00:00",
    "updated_at": "2026-03-11T17:51:46.375907+00:00",
    "estimated_hours": null,
    "sort_order": 12,
    "scrum_status": "TODO",
    "description": null,
    "sprint_week": null
  },
  {
    "id": "aa36e5b6-a623-4416-b428-f932c67f043f",
    "project_id": "95668618-c7aa-4770-a484-a1df5d8d02e7",
    "title": "Versão final",
    "completed": false,
    "completed_at": null,
    "created_at": "2026-03-10T14:46:02.755446+00:00",
    "updated_at": "2026-03-11T17:51:46.379347+00:00",
    "estimated_hours": null,
    "sort_order": 15,
    "scrum_status": "TODO",
    "description": null,
    "sprint_week": null
  },
  {
    "id": "a25cb5d5-f07b-4588-b497-8d2ce616eb7a",
    "project_id": "95668618-c7aa-4770-a484-a1df5d8d02e7",
    "title": "História do usuário",
    "completed": false,
    "completed_at": null,
    "created_at": "2026-03-10T15:05:22.804974+00:00",
    "updated_at": "2026-03-11T17:51:46.391795+00:00",
    "estimated_hours": null,
    "sort_order": 10,
    "scrum_status": "TODO",
    "description": null,
    "sprint_week": null
  },
  {
    "id": "bc7ed575-c826-4f23-96eb-f2ccb3540562",
    "project_id": "95668618-c7aa-4770-a484-a1df5d8d02e7",
    "title": "Validação e Manutenções",
    "completed": false,
    "completed_at": null,
    "created_at": "2026-03-10T14:45:03.77274+00:00",
    "updated_at": "2026-03-11T17:51:46.394074+00:00",
    "estimated_hours": null,
    "sort_order": 13,
    "scrum_status": "TODO",
    "description": null,
    "sprint_week": null
  },
  {
    "id": "6e93c70a-943c-4ccf-ba24-e4bc16651583",
    "project_id": "95668618-c7aa-4770-a484-a1df5d8d02e7",
    "title": "Backend ligado ao front",
    "completed": false,
    "completed_at": null,
    "created_at": "2026-03-10T14:43:01.115128+00:00",
    "updated_at": "2026-03-11T17:51:46.410748+00:00",
    "estimated_hours": null,
    "sort_order": 6,
    "scrum_status": "TODO",
    "description": null,
    "sprint_week": null
  },
  {
    "id": "1c53fdef-2b4b-4ef6-95b5-7240f16f2d5e",
    "project_id": "95668618-c7aa-4770-a484-a1df5d8d02e7",
    "title": "API da plataforma",
    "completed": false,
    "completed_at": null,
    "created_at": "2026-03-10T14:43:16.476905+00:00",
    "updated_at": "2026-03-11T17:51:46.419572+00:00",
    "estimated_hours": null,
    "sort_order": 8,
    "scrum_status": "TODO",
    "description": null,
    "sprint_week": null
  },
  {
    "id": "d21438c1-1fb0-4922-a468-dca8cb9e3ee2",
    "project_id": "95668618-c7aa-4770-a484-a1df5d8d02e7",
    "title": "Testes e manutenções",
    "completed": false,
    "completed_at": null,
    "created_at": "2026-03-10T14:44:36.696163+00:00",
    "updated_at": "2026-03-11T17:51:46.390911+00:00",
    "estimated_hours": null,
    "sort_order": 11,
    "scrum_status": "TODO",
    "description": null,
    "sprint_week": null
  },
  {
    "id": "5604b1f7-7a94-4ef6-a059-8f2aae270a96",
    "project_id": "95668618-c7aa-4770-a484-a1df5d8d02e7",
    "title": "Estruturar em módulos - Módulo de cadastro, login, upload...",
    "completed": false,
    "completed_at": null,
    "created_at": "2026-03-10T14:43:52.919668+00:00",
    "updated_at": "2026-03-11T17:51:46.467939+00:00",
    "estimated_hours": null,
    "sort_order": 9,
    "scrum_status": "TODO",
    "description": null,
    "sprint_week": null
  },
  {
    "id": "f416966c-d667-4d76-abca-0c9d125f1ca2",
    "project_id": "95668618-c7aa-4770-a484-a1df5d8d02e7",
    "title": "Organização de pastas da IDE",
    "completed": false,
    "completed_at": null,
    "created_at": "2026-03-10T14:44:18.844896+00:00",
    "updated_at": "2026-03-11T17:51:46.466308+00:00",
    "estimated_hours": null,
    "sort_order": 4,
    "scrum_status": "TODO",
    "description": null,
    "sprint_week": null
  },
  {
    "id": "9853cd0f-0af2-470c-9249-71608019f4ec",
    "project_id": "95668618-c7aa-4770-a484-a1df5d8d02e7",
    "title": "Definir ID Visual",
    "completed": false,
    "completed_at": null,
    "created_at": "2026-03-10T14:38:27.661463+00:00",
    "updated_at": "2026-03-11T17:51:46.475491+00:00",
    "estimated_hours": null,
    "sort_order": 1,
    "scrum_status": "TODO",
    "description": null,
    "sprint_week": null
  },
  {
    "id": "8cc7bc1b-1eb9-450a-af4d-794012952434",
    "project_id": "95668618-c7aa-4770-a484-a1df5d8d02e7",
    "title": "Banco de dados da plataforma",
    "completed": false,
    "completed_at": null,
    "created_at": "2026-03-10T14:43:08.947178+00:00",
    "updated_at": "2026-03-11T17:51:46.495276+00:00",
    "estimated_hours": null,
    "sort_order": 7,
    "scrum_status": "TODO",
    "description": null,
    "sprint_week": null
  },
  {
    "id": "1027f9bb-e74b-4dab-9108-44bfc9a09d1d",
    "project_id": "95668618-c7aa-4770-a484-a1df5d8d02e7",
    "title": "Fase DEMO",
    "completed": false,
    "completed_at": null,
    "created_at": "2026-03-10T14:45:52.082816+00:00",
    "updated_at": "2026-03-11T17:51:46.450722+00:00",
    "estimated_hours": null,
    "sort_order": 14,
    "scrum_status": "TODO",
    "description": null,
    "sprint_week": null
  },
  {
    "id": "753d391e-4004-41bb-8c5e-f9b6eeff6b03",
    "project_id": "95668618-c7aa-4770-a484-a1df5d8d02e7",
    "title": "Fazer o front-end no código",
    "completed": false,
    "completed_at": null,
    "created_at": "2026-03-10T14:41:43.41279+00:00",
    "updated_at": "2026-03-11T17:51:46.835458+00:00",
    "estimated_hours": null,
    "sort_order": 5,
    "scrum_status": "TODO",
    "description": null,
    "sprint_week": null
  },
  {
    "id": "bf7e07e3-e1f3-4480-9239-849bc08bf86a",
    "project_id": "95668618-c7aa-4770-a484-a1df5d8d02e7",
    "title": "Protótipo de alta fidelidade - Figma",
    "completed": false,
    "completed_at": null,
    "created_at": "2026-03-10T14:41:22.882223+00:00",
    "updated_at": "2026-03-11T17:51:46.836587+00:00",
    "estimated_hours": null,
    "sort_order": 3,
    "scrum_status": "TODO",
    "description": null,
    "sprint_week": null
  },
  {
    "id": "bad80be2-d2d0-4a8b-b00c-5decb1042705",
    "project_id": "95668618-c7aa-4770-a484-a1df5d8d02e7",
    "title": "Regras de negócio - Fluxograma de permissões e atividades da plataforma",
    "completed": false,
    "completed_at": null,
    "created_at": "2026-03-10T14:40:25.310363+00:00",
    "updated_at": "2026-03-11T17:51:46.840481+00:00",
    "estimated_hours": null,
    "sort_order": 2,
    "scrum_status": "TODO",
    "description": null,
    "sprint_week": null
  },
  {
    "id": "e8e611f4-b222-4028-ab2a-7669d08f0990",
    "project_id": "95668618-c7aa-4770-a484-a1df5d8d02e7",
    "title": "Planejar escopo primário da aplicação",
    "completed": false,
    "completed_at": null,
    "created_at": "2026-03-10T14:37:28.584595+00:00",
    "updated_at": "2026-03-11T17:51:46.84268+00:00",
    "estimated_hours": null,
    "sort_order": 0,
    "scrum_status": "TODO",
    "description": null,
    "sprint_week": null
  }
]